odoo/addons/currency_rate_update_xe/README.rst
odoo/addons/currency_rate_update_xe/__init__.py
odoo/addons/currency_rate_update_xe/__manifest__.py
odoo/addons/currency_rate_update_xe/i18n/currency_rate_update_xe.pot
odoo/addons/currency_rate_update_xe/i18n/es.po
odoo/addons/currency_rate_update_xe/i18n/it.po
odoo/addons/currency_rate_update_xe/models/__init__.py
odoo/addons/currency_rate_update_xe/models/res_currency_rate_provider_XE.py
odoo/addons/currency_rate_update_xe/readme/CONFIGURE.md
odoo/addons/currency_rate_update_xe/readme/CONTRIBUTORS.md
odoo/addons/currency_rate_update_xe/readme/DESCRIPTION.md
odoo/addons/currency_rate_update_xe/static/description/icon.png
odoo/addons/currency_rate_update_xe/static/description/index.html
odoo/addons/currency_rate_update_xe/tests/__init__.py
odoo/addons/currency_rate_update_xe/tests/test_currency_rate_update_xe.py
odoo_addon_currency_rate_update_xe-17.0.1.0.0.7.dist-info/METADATA
odoo_addon_currency_rate_update_xe-17.0.1.0.0.7.dist-info/WHEEL
odoo_addon_currency_rate_update_xe-17.0.1.0.0.7.dist-info/top_level.txt
odoo_addon_currency_rate_update_xe-17.0.1.0.0.7.dist-info/RECORD
